fund_insight_engine/__init__.py
fund_insight_engine/path_director.py
fund_insight_engine/bbg_retriever/__init__.py
fund_insight_engine/bbg_retriever/bbg_price.py
fund_insight_engine/classes/__init__.py
fund_insight_engine/classes/cluster.py
fund_insight_engine/classes/seasonality.py
fund_insight_engine/datamart/__init__.py
fund_insight_engine/datamart/dk.py
fund_insight_engine/datamart/ranking.py
fund_insight_engine/datamart/marketing/__init__.py
fund_insight_engine/datamart/marketing/marketing_proposal.py
fund_insight_engine/datamart/marketing/marketing_proposal_syles.py
fund_insight_engine/fund/__init__.py
fund_insight_engine/fund/fund.py
fund_insight_engine/fund/fund_consts.py
fund_insight_engine/fund/fund_utils.py
fund_insight_engine/fund_data_retriever/__init__.py
fund_insight_engine/fund_data_retriever/basis.py
fund_insight_engine/fund_data_retriever/fund_info.py
fund_insight_engine/fund_data_retriever/firm_aum/__init__.py
fund_insight_engine/fund_data_retriever/firm_aum/aum_retriever.py
fund_insight_engine/fund_data_retriever/firm_aum/aum_timeseries.py
fund_insight_engine/fund_data_retriever/firm_aum/utils.py
fund_insight_engine/fund_data_retriever/fund_bm/__init__.py
fund_insight_engine/fund_data_retriever/fund_bm/menu8186_bms.py
fund_insight_engine/fund_data_retriever/fund_codes/__init__.py
fund_insight_engine/fund_data_retriever/fund_codes/all_funds.py
fund_insight_engine/fund_data_retriever/fund_codes/aum_fund_filter.py
fund_insight_engine/fund_data_retriever/fund_codes/classes.py
fund_insight_engine/fund_data_retriever/fund_codes/classes_consts.py
fund_insight_engine/fund_data_retriever/fund_codes/divisions.py
fund_insight_engine/fund_data_retriever/fund_codes/divisions_consts.py
fund_insight_engine/fund_data_retriever/fund_codes/historical.py
fund_insight_engine/fund_data_retriever/fund_codes/main_fund_filter.py
fund_insight_engine/fund_data_retriever/fund_codes/snapshot.py
fund_insight_engine/fund_data_retriever/fund_codes/trusts.py
fund_insight_engine-1.2.7.dist-info/METADATA
fund_insight_engine-1.2.7.dist-info/WHEEL
fund_insight_engine-1.2.7.dist-info/top_level.txt
fund_insight_engine-1.2.7.dist-info/RECORD
