Metadata-Version: 2.4
Name: fund_insight_engine
Version: 1.2.7
Summary: A Python package providing utility functions for fund code management and analysis
Author: June Young Park
Author-email: juneyoungpaak@gmail.com
Classifier: Programming Language :: Python :: 3
Classifier: Programming Language :: Python :: 3.7
Classifier: Programming Language :: Python :: 3.8
Classifier: Programming Language :: Python :: 3.9
Classifier: Programming Language :: Python :: 3.10
Requires-Python: >=3.7
Requires-Dist: financial_dataset_preprocessor>=0.3.7
Requires-Dist: aws_s3_controller>=0.7.5
Requires-Dist: mongodb_controller>=0.2.6
Requires-Dist: pandas>=2.2.3
Requires-Dist: universal_timeseries_transformer>=0.3.7
Requires-Dist: timeseries_performance_calculator>=0.3.5
Requires-Dist: canonical_transformer>=0.1.5
Requires-Dist: string_date_controller>=0.3.0
Dynamic: author
Dynamic: author-email
Dynamic: classifier
Dynamic: description
Dynamic: description-content-type
Dynamic: requires-dist
Dynamic: requires-python
Dynamic: summary
